aare_core/__init__.py
aare_core/cli.py
aare_core/formula_compiler.py
aare_core/llm_parser.py
aare_core/ontology_loader.py
aare_core/persistence.py
aare_core/server.py
aare_core/smt_verifier.py
aare_core-0.3.0.dist-info/licenses/LICENSE
aare_core-0.3.0.dist-info/METADATA
aare_core-0.3.0.dist-info/WHEEL
aare_core-0.3.0.dist-info/entry_points.txt
aare_core-0.3.0.dist-info/top_level.txt
aare_core-0.3.0.dist-info/RECORD
