Metadata-Version: 2.4
Name: aare-core
Version: 0.3.0
Summary: Z3 SMT verification engine for LLM compliance
Author: aare.ai
License: MIT
Project-URL: Homepage, https://aare.ai
Project-URL: Repository, https://github.com/aare-ai/aare-core
Project-URL: Documentation, https://github.com/aare-ai/aare-core#readme
Keywords: z3,smt,verification,llm,compliance,formal-methods
Classifier: Development Status :: 4 - Beta
Classifier: Intended Audience :: Developers
Classifier: License :: OSI Approved :: MIT License
Classifier: Programming Language :: Python :: 3
Classifier: Programming Language :: Python :: 3.9
Classifier: Programming Language :: Python :: 3.10
Classifier: Programming Language :: Python :: 3.11
Classifier: Programming Language :: Python :: 3.12
Classifier: Topic :: Scientific/Engineering :: Artificial Intelligence
Classifier: Topic :: Software Development :: Quality Assurance
Requires-Python: >=3.9
License-File: LICENSE
Requires-Dist: z3-solver>=4.12.0
Requires-Dist: pydantic>=2.0.0
Provides-Extra: server
Requires-Dist: flask>=3.0.0; extra == "server"
Requires-Dist: gunicorn>=21.0.0; extra == "server"
Provides-Extra: dev
Requires-Dist: pytest>=7.0.0; extra == "dev"
Requires-Dist: pytest-cov>=4.0.0; extra == "dev"
Dynamic: license-file
